pxapi/__init__.py
pxapi/__main__.py
pxapi/pxapi.py
pxapi/stompframe.py
pxgrid_api-0.2.5.dist-info/LICENSE
pxgrid_api-0.2.5.dist-info/METADATA
pxgrid_api-0.2.5.dist-info/NOTICE
pxgrid_api-0.2.5.dist-info/WHEEL
pxgrid_api-0.2.5.dist-info/entry_points.txt
pxgrid_api-0.2.5.dist-info/top_level.txt
pxgrid_api-0.2.5.dist-info/RECORD
