Metadata-Version: 2.1
Name: pxgrid-api
Version: 0.2.5
Summary: pxGrid API library and command line tool
Author-email: Viktor Bobrov <vibobrov@cisco.com>
License: Apache License
Project-URL: Homepage, https://github.com/vbobrov/px-api
Project-URL: Documentation, https://pxgrid-api.readthedocs.io/
Keywords: pxgrid
Classifier: License :: OSI Approved :: Apache Software License
Classifier: Programming Language :: Python
Classifier: Programming Language :: Python :: 3
Requires-Python: >=3.8
License-File: LICENSE
License-File: NOTICE
Requires-Dist: requests
Requires-Dist: python-dateutil
Requires-Dist: websocket-client
